GitHub_Action_Python_Example/__init__.py
GitHub_Action_Python_Example/__version__.py
GitHub_Action_Python_Example/client.py
GitHub_Action_Python_Example-1.0.2.dist-info/LICENSE
GitHub_Action_Python_Example-1.0.2.dist-info/METADATA
GitHub_Action_Python_Example-1.0.2.dist-info/WHEEL
GitHub_Action_Python_Example-1.0.2.dist-info/top_level.txt
GitHub_Action_Python_Example-1.0.2.dist-info/RECORD
